flowtastic/__init__.py
flowtastic/_deserialization_combo.py
flowtastic/app.py
flowtastic/cli/__init__.py
flowtastic/cli/cli.py
flowtastic/cli/colors.py
flowtastic/cli/local_environment.py
flowtastic/config.py
flowtastic/logger.py
flowtastic/message/__init__.py
flowtastic/message/base.py
flowtastic/message/exceptions.py
flowtastic/message/json_message.py
flowtastic/publish.py
flowtastic/py.typed
flowtastic/types.py
flowtastic/utils/__init__.py
flowtastic/utils/asynchronous.py
flowtastic/utils/list.py
flowtastic/utils/pydantic_models.py
flowtastic-0.0.1a0.dist-info/entry_points.txt
flowtastic-0.0.1a0.dist-info/LICENSE
flowtastic-0.0.1a0.dist-info/WHEEL
flowtastic-0.0.1a0.dist-info/METADATA
flowtastic-0.0.1a0.dist-info/RECORD
