Metadata-Version: 2.1
Name: flowtastic
Version: 0.0.1a0
Summary: Python Stream Processing (Faust like!) backed by pydantic.
Home-page: https://github.com/gabrielmbmb/flowtastic
License: MIT
Author: Gabriel Martín Blázquez
Author-email: gmartinbdev@gmail.com
Requires-Python: >=3.6,<4.0
Classifier: Development Status :: 4 - Beta
Classifier: Framework :: AsyncIO
Classifier: Intended Audience :: Developers
Classifier: Intended Audience :: Education
Classifier: Intended Audience :: Financial and Insurance Industry
Classifier: Intended Audience :: Information Technology
Classifier: Intended Audience :: Science/Research
Classifier: Intended Audience :: System Administrators
Classifier: License :: OSI Approved :: MIT License
Classifier: Programming Language :: Python :: 3
Classifier: Programming Language :: Python :: 3 :: Only
Classifier: Programming Language :: Python :: 3.10
Classifier: Programming Language :: Python :: 3.6
Classifier: Programming Language :: Python :: 3.7
Classifier: Programming Language :: Python :: 3.8
Classifier: Programming Language :: Python :: 3.9
Classifier: Topic :: System :: Distributed Computing
Classifier: Topic :: System :: Networking
Classifier: Typing :: Typed
Provides-Extra: orjson
Requires-Dist: aiokafka (>=0.7.2,<0.8.0)
Requires-Dist: orjson (>=3.6.1,<4.0.0); extra == "orjson"
Requires-Dist: pydantic (>=1.9.1,<2.0.0)
Requires-Dist: rich (>=12.4.4,<13.0.0)
Project-URL: Documentation, https://flowtastic.gabrielmb.com
Project-URL: Repository, https://github.com/gabrielmbmb/flowtastic
